setup.cfg
setup.py
tempodb/__init__.py
tempodb/client.py
tempodb/endpoint.py
tempodb/response.py
tempodb.egg-info/PKG-INFO
tempodb.egg-info/SOURCES.txt
tempodb.egg-info/dependency_links.txt
tempodb.egg-info/requires.txt
tempodb.egg-info/top_level.txt
tempodb/protocol/__init__.py
tempodb/protocol/cursor.py
tempodb/protocol/objects.py
tempodb/protocol/protocol.py
tempodb/temporal/__init__.py
tempodb/temporal/validate.py