Metadata-Version: 1.0
Name: tempodb
Version: 1.0.1
Summary: A client for the TempoDB API
Home-page: http://github.com/tempodb/tempodb-python/
Author: TempoDB Inc
Author-email: dev@tempo-db.com
License: UNKNOWN
Platform: UNKNOWN
